Workbook

Sheet Summary
A1: PIGORS v. ALL — Damages Analysis
A2: Grand Total Dashboard — All Lanes
A4: Category | B4: Lane A (Custody) | C4: Lane B (Housing) | D4: Lane D (PPO) | E4: Lane E (Misconduct) | F4: Federal §1983 | G4: GRAND TOTAL
A5: Economic Low | B5: ='Lane A — Watson Family'!C20 | C5: ='Lane B — Housing'!E31+'Lane B — Housing'!E42 | D5: 0 | E5: ='Lane E — Misconduct'!C16 | F5: ='Lane E — Misconduct'!C17 | G5: =SUM(B5:F5)
A6: Economic High | B6: ='Lane A — Watson Family'!D20 | C6: ='Lane B — Housing'!F31+'Lane B — Housing'!F42 | D6: 0 | E6: ='Lane E — Misconduct'!D16 | F6: ='Lane E — Misconduct'!D17 | G6: =SUM(B6:F6)
A7: Non-Economic Low | B7: ='Lane A — Watson Family'!E20 | C7: ='Lane B — Housing'!G31+'Lane B — Housing'!E43 | D7: 0 | E7: ='Lane E — Misconduct'!E16 | F7: =0 | G7: =SUM(B7:F7)
A8: Non-Economic High | B8: ='Lane A — Watson Family'!F20 | C8: ='Lane B — Housing'!H31+'Lane B — Housing'!F43 | D8: 0 | E8: ='Lane E — Misconduct'!F16 | F8: =0 | G8: =SUM(B8:F8)
A9: Punitive / Treble Low | B9: ='Lane A — Watson Family'!G20 | C9: =0 | D9: 0 | E9: ='Lane E — Misconduct'!G16 | F9: =0 | G9: =SUM(B9:F9)
A10: Punitive / Treble High | B10: ='Lane A — Watson Family'!H20 | C10: =0 | D10: 0 | E10: ='Lane E — Misconduct'!H16 | F10: =0 | G10: =SUM(B10:F10)
A12: TOTAL LOW | B12: =B5+B7+B9 | C12: =C5+C7+C9 | D12: =D5+D7+D9 | E12: =E5+E7+E9 | F12: =F5+F7+F9 | G12: =G5+G7+G9
A13: TOTAL HIGH | B13: =B6+B8+B10 | C13: =C6+C8+C10 | D13: =D6+D8+D10 | E13: =E6+E8+E10 | F13: =F6+F8+F10 | G13: =G6+G8+G10
A16: Sensitivity Analysis
A17: Multiplier | B17: Lane A | C17: Lane B | D17: Lane D | E17: Lane E | F17: Federal | G17: TOTAL
A18: 50% | B18: =B13*0.5 | C18: =C13*0.5 | D18: =D13*0.5 | E18: =E13*0.5 | F18: =F13*0.5 | G18: =SUM(B18:F18)
A19: 75% | B19: =B13*0.75 | C19: =C13*0.75 | D19: =D13*0.75 | E19: =E13*0.75 | F19: =F13*0.75 | G19: =SUM(B19:F19)
A20: 100% | B20: =B13*1.0 | C20: =C13*1.0 | D20: =D13*1.0 | E20: =E13*1.0 | F20: =F13*1.0 | G20: =SUM(B20:F20)
A21: 125% | B21: =B13*1.25 | C21: =C13*1.25 | D21: =D13*1.25 | E21: =E13*1.25 | F21: =F13*1.25 | G21: =SUM(B21:F21)

Sheet Lane A — Watson Family
A1: Lane A — Watson Family Tort Damages (13 Counts)
A2: Defendants: Emily A. Watson, Albert Watson, Lori Watson, Cody Watson, Lane A. Watson
C4: Economic | E4: Non-Economic | G4: Punitive
A5: Count | B5: Cause of Action | C5: Low | D5: High | E5: Low | F5: High | G5: Low | H5: High
A6: I | B6: Civil Conspiracy (all) | C6: 10000 | D6: 50000 | E6: 25000 | F6: 100000 | G6: 0 | H6: 0
A7: II | B7: IIED (Emily) | C7: 0 | D7: 0 | E7: 50000 | F7: 250000 | G7: 25000 | H7: 100000
A8: III | B8: Tortious Interference—Parental (all) | C8: 15000 | D8: 75000 | E8: 50000 | F8: 200000 | G8: 0 | H8: 0
A9: IV | B9: Tortious Interference—Custody (Emily) | C9: 10000 | D9: 50000 | E9: 25000 | F9: 100000 | G9: 0 | H9: 0
A10: V | B10: Defamation Per Se (Emily) | C10: 5000 | D10: 25000 | E10: 25000 | F10: 100000 | G10: 10000 | H10: 50000
A11: VI | B11: Slander (Emily, Lori) | C11: 5000 | D11: 15000 | E11: 15000 | F11: 50000 | G11: 0 | H11: 0
A12: VII | B12: Malicious Prosecution (Emily) | C12: 10000 | D12: 40000 | E12: 25000 | F12: 75000 | G12: 10000 | H12: 50000
A13: VIII | B13: Abuse of Process (Emily, Berry) | C13: 10000 | D13: 30000 | E13: 20000 | F13: 60000 | G13: 10000 | H13: 40000
A14: IX | B14: Fraud on Court (Emily, Berry) | C14: 5000 | D14: 25000 | E14: 15000 | F14: 50000 | G14: 25000 | H14: 100000
A15: X | B15: Conversion (Emily) | C15: 5000 | D15: 15000 | E15: 5000 | F15: 15000 | G15: 0 | H15: 0
A16: XI | B16: Unjust Enrichment (Emily) | C16: 5000 | D16: 20000 | E16: 0 | F16: 0 | G16: 0 | H16: 0
A17: XII | B17: NIED (all) | C17: 0 | D17: 0 | E17: 25000 | F17: 100000 | G17: 0 | H17: 0
A18: XIII | B18: Loss of Companionship (Emily) | C18: 0 | D18: 0 | E18: 50000 | F18: 200000 | G18: 0 | H18: 0
B20: SUBTOTALS | C20: =SUM(C6:C18) | D20: =SUM(D6:D18) | E20: =SUM(E6:E18) | F20: =SUM(F6:F18) | G20: =SUM(G6:G18) | H20: =SUM(H6:H18)
B22: GRAND TOTAL LOW | C22: =C20+E20+G20
B23: GRAND TOTAL HIGH | C23: =D20+F20+H20

Sheet Lane B — Housing
A1: Lane B — Housing Mega-Complaint (22 Counts)
A2: Defs: Shady Oaks MHP LLC, Homes of America LLC, Alden Global, Partridge Equity, VRM Capital, Cricklewood, VanDam, Browley, Davis
E4: Economic | G4: Non-Economic
A5: Count | B5: Cause of Action | C5: Statute | D5: Treble? | E5: Low | F5: High | G5: Low | H5: High
A6: I | B6: Conversion | C6: MCL 600.2919a | D6: YES ×3 | E6: 10000 | F6: 27500 | G6: 0 | H6: 0
A7: II | B7: Fraud | C7: MCL 566.34 | D7: No | E7: 15000 | F7: 75000 | G7: 25000 | H7: 100000
A8: III | B8: Tortious Interference | C8: Common law | D8: No | E8: 20000 | F8: 35000 | G8: 25000 | H8: 50000
A9: IV | B9: Mobile Home Commission Act | C9: MCL 125.2301 | D9: No | E9: 10000 | F9: 40000 | G9: 10000 | H9: 40000
A10: V | B10: Ultra Vires | C10: MCL 450.4802 | D10: No | E10: 0 | F10: 0 | G10: 0 | H10: 0
A11: VI | B11: Unjust Enrichment | C11: Equity | D11: No | E11: 6000 | F11: 6000 | G11: 0 | H11: 0
A12: VII | B12: Civil Conspiracy | C12: Common law | D12: No | E12: 0 | F12: 0 | G12: 0 | H12: 0
A13: VIII | B13: Veil Piercing | C13: Equity | D13: No | E13: 0 | F13: 0 | G13: 0 | H13: 0
A14: IX | B14: Michigan RICO | C14: MCL 750.159i | D14: YES ×3 | E14: 100000 | F14: 500000 | G14: 100000 | H14: 500000
A15: X | B15: Constructive Eviction | C15: Common law | D15: No | E15: 15000 | F15: 60000 | G15: 25000 | H15: 100000
A16: XI | B16: Retaliatory Eviction | C16: MCL 600.5720 | D16: No | E16: 10000 | F16: 40000 | G16: 10000 | H16: 40000
A17: XII | B17: Consumer Protection | C17: MCL 445.903 | D17: YES ×3 | E17: 25000 | F17: 100000 | G17: 0 | H17: 0
... A27: XXII | B27: Fraud on Court | C27: Equity | D27: No | E27: 0 | F27: 0 | G27: 0 | H27: 0
B29: ─── BASE TOTALS ───
B30: SUBTOTALS (before treble)
B31: BASE TOTALS | E31: =SUM(E6:E27) | F31: =SUM(F6:F27) | G31: =SUM(G6:G27) | H31: =SUM(H6:H27)
B33: ─── TREBLE / ENHANCED DAMAGES ───
B34: Treble Calculations
B35: Count | C35: Base Low | D35: Base High | E35: Trebled Low (×3) | F35: Trebled High (×3) | G35: Additional Low | H35: Additional High
B36: I — Conversion | C36: =E6+G6 | D36: =F6+H6 | E36: =C36*3 | F36: =D36*3 | G36: =E36-C36 | H36: =F36-D36
B37: IX — Michigan RICO | C37: =E14+G14 | D37: =F14+H14 | E37: =C37*3 | F37: =D37*3 | G37: =E37-C37 | H37: =F37-D37
B38: XII — Consumer Prot. | C38: =E17+G17 | D38: =F17+H17 | E38: =C38*3 | F38: =D38*3 | G38: =E38-C38 | H38: =F38-D38
B39: XX — Fair Housing | C39: =E25+G25 | D39: =F25+H25 | E39: =C39*3 | F39: =D39*3 | G39: =E39-C39 | H39: =F39-D39
B40: TREBLE ADDITIONAL TOTALS | E40: =SUM(E36:E39) | F40: =SUM(F36:F39) | G40: =SUM(G36:G39) | H40: =SUM(H36:H39)
B42: Treble Additional — Economic | E42: =E6*2+E14*2+E17*2+E25*2 | F42: =F6*2+F14*2+F17*2+F25*2
B43: Treble Additional — Non-Economic | E43: =G6*2+G14*2+G17*2+G25*2 | F43: =H6*2+H14*2+H17*2+H25*2
B45: GRAND TOTAL LOW (with treble) | E45: =E31+E42+E43
B46: GRAND TOTAL HIGH (with treble) | E46: =F31+F42+F43

Sheet Lane E — Misconduct
A1: Lane E — Judicial Misconduct / Federal §1983
A2: Defendants: Hon. McNeill, Atty Berry, FOC Rusco, Muskegon County
C4: Economic | E4: Non-Economic | G4: Punitive
A5: Count | B5: Against | C5: Low | D5: High | E5: Low | F5: High | G5: Low | H5: High
A6: Due Process Violation | B6: McNeill | C6: 25000 | D6: 100000 | E6: 75000 | F6: 300000 | G6: 50000 | H6: 200000
A7: Parental Liberty | B7: McNeill | C7: 15000 | D7: 75000 | E7: 100000 | F7: 500000 | G7: 50000 | H7: 250000
A8: §1983 Conspiracy | B8: Watson/Berry/McNeill | C8: 20000 | D8: 80000 | E8: 50000 | F8: 200000 | G8: 25000 | H8: 100000
A9: Monell Liability | B9: Muskegon County | C9: 50000 | D9: 250000 | E9: 100000 | F9: 500000 | G9: N/A | H9: N/A
A10: Equal Protection | B10: McNeill | C10: 10000 | D10: 50000 | E10: 50000 | F10: 200000 | G10: 25000 | H10: 100000
A11: 1st Amend. Retaliation | B11: McNeill | C11: 10000 | D11: 50000 | E11: 50000 | F11: 200000 | G11: 25000 | H11: 100000
A12: State Tort Claims | B12: Watson/Berry | C12: 15000 | D12: 60000 | E12: 25000 | F12: 100000 | G12: 10000 | H12: 50000
B14: ─── TOTALS ───
B16: SUBTOTALS | C16: =SUM(C6:C12) | D16: =SUM(D6:D12) | E16: =SUM(E6:E12) | F16: =SUM(F6:F12) | G16: =SUM(G6:G12) | H16: =SUM(H6:H12)
A17: §1988 | B17: Attorney Fees (42 USC §1988) | C17: 50000 | D17: 200000
B19: GRAND TOTAL LOW | C19: =C16+E16+G16+C17
B20: GRAND TOTAL HIGH | C20: =D16+F16+H16+D17

Sheet Sensitivity Analysis
A1: Sensitivity Analysis — Recovery Scenarios
A2: All values are formulas referencing Summary sheet totals
A4: Recovery % | B4: Lane A | C4: Lane B (no treble) | D4: Lane B (with treble) | E4: Lane E | F4: Federal §1988 | G4: TOTAL (no treble) | H4: TOTAL (with treble)
A5: 25% | B5: ='Summary'!B13*0.25 | C5: =('Lane B — Housing'!E31+'Lane B — Housing'!F31+'Lane B — Housing'!G31+'Lane B — Housing'!H31)/2*0.25 | D5: ='Summary'!C13*0.25 | E5: ='Summary'!E13*0.25 | F5: ='Summary'!F13*0.25 | G5: =B5+C5+E5+F5 | H5: =B5+D5+E5+F5
A6: 50% | B6: ='Summary'!B13*0.5 | C6: =('Lane B — Housing'!E31+'Lane B — Housing'!F31+'Lane B — Housing'!G31+'Lane B — Housing'!H31)/2*0.5 | D6: ='Summary'!C13*0.5 | E6: ='Summary'!E13*0.5 | F6: ='Summary'!F13*0.5 | G6: =B6+C6+E6+F6 | H6: =B6+D6+E6+F6
A7: 75% | B7: ='Summary'!B13*0.75 | C7: =('Lane B — Housing'!E31+'Lane B — Housing'!F31+'Lane B — Housing'!G31+'Lane B — Housing'!H31)/2*0.75 | D7: ='Summary'!C13*0.75 | E7: ='Summary'!E13*0.75 | F7: ='Summary'!F13*0.75 | G7: =B7+C7+E7+F7 | H7: =B7+D7+E7+F7
A8: 100% | B8: ='Summary'!B13*1.0 | C8: =('Lane B — Housing'!E31+'Lane B — Housing'!F31+'Lane B — Housing'!G31+'Lane B — Housing'!H31)/2*1.0 | D8: ='Summary'!C13*1.0 | E8: ='Summary'!E13*1.0 | F8: ='Summary'!F13*1.0 | G8: =B8+C8+E8+F8 | H8: =B8+D8+E8+F8
A11: LOW Estimate Sensitivity
A12: Recovery % | B12: Lane A | C12: Lane B (no treble) | D12: Lane B (with treble) | E12: Lane E | F12: Federal §1988 | G12: TOTAL (no treble) | H12: TOTAL (with treble)
A13: 25% | B13: ='Summary'!B12*0.25 | C13: =('Lane B — Housing'!E31+'Lane B — Housing'!G31)*0.25 | D13: ='Summary'!C12*0.25 | E13: ='Summary'!E12*0.25 | F13: ='Summary'!F12*0.25 | G13: =B13+C13+E13+F13 | H13: =B13+D13+E13+F13
A14: 50% | B14: ='Summary'!B12*0.5 | C14: =('Lane B — Housing'!E31+'Lane B — Housing'!G31)*0.5 | D14: ='Summary'!C12*0.5 | E14: ='Summary'!E12*0.5 | F14: ='Summary'!F12*0.5 | G14: =B14+C14+E14+F14 | H14: =B14+D14+E14+F14
A15: 75% | B15: ='Summary'!B12*0.75 | C15: =('Lane B — Housing'!E31+'Lane B — Housing'!G31)*0.75 | D15: ='Summary'!C12*0.75 | E15: ='Summary'!E12*0.75 | F15: ='Summary'!F12*0.75 | G15: =B15+C15+E15+F15 | H15: =B15+D15+E15+F15
A16: 100% | B16: ='Summary'!B12*1.0 | C16: =('Lane B — Housing'!E31+'Lane B — Housing'!G31)*1.0 | D16: ='Summary'!C12*1.0 | E16: ='Summary'!E12*1.0 | F16: ='Summary'!F12*1.0 | G16: =B16+C16+E16+F16 | H16: =B16+D16+E16+F16

Sheet Per-Defendant Liability
A1: Per-Defendant Liability Exposure
A2: 19 Defendants Across All Lanes — Joint & Several Liability Analysis
A4: # | B4: Defendant | C4: Lane(s) | D4: Joint & Several? | E4: Individual Low | F4: Individual High | G4: Notes
A5: 1 | B5: Emily A. Watson | C5: A, D | D5: Yes | E5: 80000 | F5: 455000 | G5: Primary — all 13 counts; PPO respondent
A6: 2 | B6: Albert Watson | C6: A | D6: Yes (conspiracy) | E6: 25000 | F6: 100000 | G6: Counts I, III, XII
A7: 3 | B7: Lori Watson | C7: A | D7: Yes (conspiracy) | E7: 30000 | F7: 115000 | G7: Counts I, III, VI, XII
A8: 4 | B8: Cody Watson | C8: A | D8: Yes (conspiracy) | E8: 25000 | F8: 100000 | G8: Counts I, III, XII
A9: 5 | B9: Lane A. Watson | C9: A | D9: Yes (conspiracy) | E9: 25000 | F9: 100000 | G9: Counts I, III, XII
A10: 6 | B10: Atty Kimberly Berry | C10: A, E | D10: Yes | E10: 40000 | F10: 230000 | G10: Counts VIII, IX; §1983 conspiracy
A11: 7 | B11: Shady Oaks MHP LLC | C11: B | D11: Yes | E11: 100000 | F11: 500000 | G11: Primary housing defendant
A12: 8 | B12: Homes of America LLC | C12: B | D12: Yes | E12: 100000 | F12: 500000 | G12: Parent entity — veil piercing
A13: 9 | B13: Alden Global Capital | C13: B | D13: Yes | E13: 100000 | F13: 500000 | G13: Ultimate parent — RICO
A14: 10 | B14: Partridge Equity | C14: B | D14: Yes | E14: 50000 | F14: 250000 | G14: Management entity
A15: 11 | B15: VRM Capital | C15: B | D15: Yes | E15: 50000 | F15: 250000 | G15: Capital entity
A16: 12 | B16: Cricklewood MHP | C16: B | D16: Yes | E16: 50000 | F16: 250000 | G16: Related park entity
... A23: 19 | B23: Unknown Doe Defendants | C23: C | D23: TBD | E23: 0 | F23: 0 | G23: Placeholder for unnamed co-conspirators
B25: TOTAL INDIVIDUAL EXPOSURE | E25: =SUM(E5:E23) | F25: =SUM(F5:F23)
B27: NOTE: Joint & several liability means each defendant may be liable for the FULL amount of damages attributable to the joint tortfeasors, not just their individual share.
